CosRayModifiedISO/CosRayModifiedISO.py
CosRayModifiedISO/__init__.py
CosRayModifiedISO/internalFunctions/__init__.py
CosRayModifiedISO/internalFunctions/importingNMdata.py
CosRayModifiedISO/internalFunctions/miscellaneous.py
CosRayModifiedISO/internalFunctions/pythonModifiedISO.py
CosRayModifiedISO/internalFunctions/rigidityEnergyConversionFunctions.py
CosRayModifiedISO/internalFunctions/spectrumHandling.py
CosRayModifiedISO/neutronMonitorData/OULUinputData.pkl
tests/__init__.py
tests/test_DLRISOmodel.py
cosraymodifiediso-1.2.10.dist-info/LICENSE
cosraymodifiediso-1.2.10.dist-info/METADATA
cosraymodifiediso-1.2.10.dist-info/WHEEL
cosraymodifiediso-1.2.10.dist-info/top_level.txt
cosraymodifiediso-1.2.10.dist-info/RECORD
