Metadata-Version: 2.2
Name: CosRayModifiedISO
Version: 1.2.10
Summary: A Python library for acquiring galactic cosmic ray spectra at Earth from the ISO model as modified by DLR. All the details and equations about this model can be found in Matthiae et al., A ready-to-use galactic cosmic ray model, Advances in Space Research 51.3 (2013): 329-338, https://doi.org/10.1016/j.asr.2012.09.022 .
Home-page: https://github.com/ssc-maire/CosRayModifiedISO
Author: Space Environment and Protection Group, University of Surrey
License: CC BY-NC-SA 4.0
Keywords: space physics galactic cosmic ray
License-File: LICENSE
Requires-Dist: importlib_resources>=5.10.0
Requires-Dist: numba>=0.56.4
Requires-Dist: numpy>=1.21.6
Requires-Dist: pandas>=1.3.5
Requires-Dist: setuptools>=45.2.0
Dynamic: author
Dynamic: description
Dynamic: description-content-type
Dynamic: home-page
Dynamic: keywords
Dynamic: license
Dynamic: requires-dist
Dynamic: summary
